metaloaders/__init__.py
metaloaders/cloudformation.py
metaloaders/exceptions.py
metaloaders/json.py
metaloaders/model.py
metaloaders/py.typed
metaloaders/yaml.py
metaloaders-20.9.2566091.dist-info/LICENSE.md
metaloaders-20.9.2566091.dist-info/WHEEL
metaloaders-20.9.2566091.dist-info/METADATA
metaloaders-20.9.2566091.dist-info/RECORD
